asimov_gwdata-0.6.3.dist-info/licenses/LICENSE
datafind/__init__.py
datafind/asimov.py
datafind/calibration.py
datafind/datafind_template.yml
datafind/frames.py
datafind/main.py
datafind/metafiles.py
datafind/utils.py
asimov_gwdata-0.6.3.dist-info/METADATA
asimov_gwdata-0.6.3.dist-info/WHEEL
asimov_gwdata-0.6.3.dist-info/entry_points.txt
asimov_gwdata-0.6.3.dist-info/top_level.txt
asimov_gwdata-0.6.3.dist-info/RECORD
