Metadata-Version: 2.4
Name: asimov-gwdata
Version: 0.6.3
Summary: An asimov plugin to make downloading gravitational wave data easier
Author-email: Daniel Williams <daniel.williams@ligo.org>
License: MIT
Project-URL: Source code, https://git.ligo.org/asimov/asimov-gwdatahelp
Classifier: Programming Language :: Python :: 3
Classifier: License :: OSI Approved :: MIT License
Classifier: Operating System :: OS Independent
Requires-Python: >=3.7
License-File: LICENSE
Requires-Dist: gwosc
Requires-Dist: asimov>=0.4.0
Requires-Dist: pesummary
Requires-Dist: numpy
Requires-Dist: requests
Requires-Dist: click
Requires-Dist: igwn-auth-utils
Requires-Dist: requests-pelican
Requires-Dist: requests-scitokens>=0.1.0
Provides-Extra: docs
Requires-Dist: sphinx; extra == "docs"
Requires-Dist: kentigern; extra == "docs"
Provides-Extra: rift
Requires-Dist: rift; extra == "rift"
Dynamic: license-file
